sndwch/__init__.py
sndwch/test.py
sndwch-0.2.0.dist-info/METADATA
sndwch-0.2.0.dist-info/WHEEL
sndwch-0.2.0.dist-info/top_level.txt
sndwch-0.2.0.dist-info/RECORD
