Metadata-Version: 2.1
Name: sndwch
Version: 0.2.0
Summary: A tool for easily manipulating strings with patterns using the "Sandwich Method"
Home-page: https://github.co.jp/
Author: bib_inf
Author-email: contact.bibinf@gmail.com
License: CC0 v1.0
Classifier: Programming Language :: Python :: 3
Classifier: Topic :: Software Development :: Libraries
Classifier: License :: CC0 1.0 Universal (CC0 1.0) Public Domain Dedication
Requires-Dist: ezpip
